exobrain/README.md
exobrain/actions/README.md
exobrain/actions/client/__about__.py
exobrain/actions/client/__init__.py
exobrain/actions/client/accessor.py
exobrain/actions/client/py.typed
exobrain/actions/client/http_client/__init__.py
exobrain/actions/client/http_client/exceptions.py
exobrain/actions/client/http_client/flask_adapter.py
exobrain/actions/client/http_client/httpx_adapter.py
exobrain/actions/client/http_client/interfaces.py
exobrain/actions/client/http_client/requests_adapter.py
exobrain_actions_client-0.2.0.dist-info/METADATA
exobrain_actions_client-0.2.0.dist-info/WHEEL
exobrain_actions_client-0.2.0.dist-info/licenses/LICENSE.md
exobrain_actions_client-0.2.0.dist-info/RECORD
