Metadata-Version: 2.4
Name: exobrain-actions-client
Version: 0.2.0
Summary: REST API client for interacting with Exobrain Actions services, providing access to action management endpoints.
Project-URL: Documentation, https://github.com/arnaudmorvan-dfya/exobrain-actions-client#readme
Project-URL: Issues, https://github.com/arnaudmorvan-dfya/exobrain-actions-client/issues
Project-URL: Source, https://github.com/arnaudmorvan-dfya/exobrain-actions-client
Author-email: Laurent LAPORTE <laurent@dfya.io>
License: Copyright © 2025-present DFYA SAS, All rights reserved.
License-File: LICENSE.md
Classifier: Development Status :: 4 - Beta
Classifier: License :: Other/Proprietary License
Classifier: Programming Language :: Python
Classifier: Programming Language :: Python :: 3.12
Requires-Python: >=3.12
Requires-Dist: exobrain-actions-schemas>=0.2.0
